immunity_python_agent/__init__.py
immunity_python_agent/version.py
immunity_python_agent/api/__init__.py
immunity_python_agent/api/openapi.py
immunity_python_agent/assess/__init__.py
immunity_python_agent/assess/c_api_hook.py
immunity_python_agent/assess/common_hook.py
immunity_python_agent/assess/ctypes_hook.py
immunity_python_agent/assess/patch.py
immunity_python_agent/assess_ext/c_api.c
immunity_python_agent/assess_ext/c_api.cpython-312-i386-linux-gnu.so
immunity_python_agent/assess_ext/libfunchook.so.1
immunity_python_agent/assess_ext/logger.c
immunity_python_agent/assess_ext/patch.c
immunity_python_agent/assess_ext/patch/cast.c
immunity_python_agent/assess_ext/patch/concat.c
immunity_python_agent/assess_ext/patch/str_cformat.c
immunity_python_agent/assess_ext/patch/str_fstring.c
immunity_python_agent/cli/__init__.py
immunity_python_agent/cli/run.py
immunity_python_agent/common/__init__.py
immunity_python_agent/common/logger.py
immunity_python_agent/context/__init__.py
immunity_python_agent/context/request.py
immunity_python_agent/context/request_context.py
immunity_python_agent/context/tracker.py
immunity_python_agent/middlewares/__init__.py
immunity_python_agent/middlewares/base_middleware.py
immunity_python_agent/middlewares/django_middleware.py
immunity_python_agent/middlewares/flask_middleware.py
immunity_python_agent/policy/__init__.py
immunity_python_agent/policy/deal_data.py
immunity_python_agent/policy/policy.py
immunity_python_agent/policy/tracking.py
immunity_python_agent/setting/__init__.py
immunity_python_agent/setting/config.py
immunity_python_agent/setting/const.py
immunity_python_agent/setting/setting.py
immunity_python_agent/utils/__init__.py
immunity_python_agent/utils/scope.py
immunity_python_agent/utils/singleton.py
immunity_python_agent/utils/system_info.py
immunity_python_agent/utils/utils.py
immunity_python_agent-2.0.0a1.data/scripts/immunity-ctl
immunity_python_agent-2.0.0a1.dist-info/METADATA
immunity_python_agent-2.0.0a1.dist-info/WHEEL
immunity_python_agent-2.0.0a1.dist-info/entry_points.txt
immunity_python_agent-2.0.0a1.dist-info/top_level.txt
immunity_python_agent-2.0.0a1.dist-info/RECORD
