Metadata-Version: 2.4
Name: immunity_python_agent
Version: 2.0.0a1
Summary: Immunity IAST Agent for Python
Home-page: https://light-hat.github.io/immunity/
Author: light-hat
Author-email: l1ghth4t@gmail.com
License: GNU General Public License v3
Classifier: Environment :: Web Environment
Classifier: Framework :: Django
Classifier: Framework :: Flask
Classifier: Intended Audience :: Developers
Classifier: License :: OSI Approved :: GNU General Public License v3 (GPLv3)
Classifier: Operating System :: OS Independent
Classifier: Programming Language :: Python
Classifier: Programming Language :: Python :: 3
Classifier: Programming Language :: Python :: 3 :: Only
Classifier: Topic :: Internet :: WWW/HTTP
Classifier: Topic :: Internet :: WWW/HTTP :: Dynamic Content
Requires-Python: >=3.6
Requires-Dist: psutil>=5.8.0
Requires-Dist: requests>=2.25.1
Requires-Dist: setuptools<81
